XProperties/__init__.py
XProperties/xproperties.py
XProperties-2.0.10.dist-info/LICENSE
XProperties-2.0.10.dist-info/METADATA
XProperties-2.0.10.dist-info/WHEEL
XProperties-2.0.10.dist-info/top_level.txt
XProperties-2.0.10.dist-info/RECORD
