Metadata-Version: 2.1
Name: XProperties
Version: 2.0.10
Summary: Cross-Language .properties file parser
Home-page: https://github.com/Duelit/XProperties
Author: Duelit
Author-email: jyoon07dev@gmail.com
Maintainer: Duelit
Maintainer-email: jyoon07dev@gmail.com
License: UNKNOWN
Keywords: xproperties
Platform: UNKNOWN
Classifier: License :: OSI Approved :: GNU Lesser General Public License v2 or later (LGPLv2+)
Classifier: Operating System :: Microsoft :: Windows
Classifier: Operating System :: MacOS :: MacOS X
Classifier: Operating System :: POSIX
Classifier: Programming Language :: Python :: 3.7
Classifier: Programming Language :: Python :: 3.8
Classifier: Programming Language :: Python :: 3.9
Classifier: Programming Language :: Python :: 3.10
Requires-Python: >=3.7
License-File: LICENSE
